natural_keys/__init__.py
natural_keys/models.py
natural_keys/serializers.py
natural_keys-2.1.1.dist-info/LICENSE
natural_keys-2.1.1.dist-info/METADATA
natural_keys-2.1.1.dist-info/WHEEL
natural_keys-2.1.1.dist-info/top_level.txt
natural_keys-2.1.1.dist-info/RECORD
