Metadata-Version: 2.1
Name: natural-keys
Version: 2.1.1
Summary: Enhanced support for natural keys in Django and Django REST Framework.
Author-email: "S. Andrew Sheppard" <andrew@wq.io>
License: MIT
Project-URL: Homepage, https://github.com/wq/django-natural-keys
Project-URL: Documentation, https://wq.io/
Project-URL: Source, https://github.com/wq/django-natural-keys
Project-URL: Release Notes, https://github.com/wq/django-natural-keys/releases
Project-URL: Issues, https://github.com/wq/django-natural-keys/issues
Project-URL: Tests, https://github.com/wq/django-natural-keys/actions/workflows/test.yml
Classifier: Development Status :: 5 - Production/Stable
Classifier: Environment :: Web Environment
Classifier: License :: OSI Approved :: MIT License
Classifier: Natural Language :: English
Classifier: Programming Language :: Python :: 3
Classifier: Programming Language :: Python :: 3.8
Classifier: Programming Language :: Python :: 3.9
Classifier: Programming Language :: Python :: 3.10
Classifier: Programming Language :: Python :: 3.11
Classifier: Programming Language :: Python :: 3.12
Classifier: Framework :: Django
Classifier: Framework :: Django :: 4.0
Classifier: Framework :: Django :: 4.1
Classifier: Framework :: Django :: 4.2
Classifier: Framework :: Django :: 5.0
Classifier: Topic :: Database
Requires-Python: >=3.8
License-File: LICENSE
Requires-Dist: html-json-forms>=1.0.0
